COPYRIGHT
LICENSE
MANIFEST.in
README
setup.cfg
setup.py
numword/__init__.py
numword/numword_base.py
numword/numword_de.py
numword/numword_en.py
numword/numword_en_gb.py
numword/numword_es.py
numword/numword_eu.py
numword/numword_fr.py
numword/numword_fr_be.py
numword/tests.py
psk_numword.egg-info/PKG-INFO
psk_numword.egg-info/SOURCES.txt
psk_numword.egg-info/dependency_links.txt
psk_numword.egg-info/top_level.txt
tests/__init__.py
tests/test_escpos.py