Metadata-Version: 1.1
Name: psk-numword
Version: 0.5
Summary: Python modules to convert numbers to words
Home-page: https://bitbucket.org/presik/psk_numword
Author: Presik Technologies
Author-email: gerente@presik.com
License: LGPL
Download-URL: https://bitbucket.org/presik/psk_numword/downloads
Platform: UNKNOWN
Classifier: Development Status :: 5 - Production/Stable
Classifier: Intended Audience :: Developers
Classifier: License :: OSI Approved :: GNU Library or Lesser General Public License (LGPL)
Classifier: Natural Language :: English
Classifier: Natural Language :: French
Classifier: Natural Language :: German
Classifier: Natural Language :: Spanish
Classifier: Operating System :: OS Independent
Classifier: Programming Language :: Python :: 2.7
Classifier: Programming Language :: Python :: 3
Classifier: Topic :: Software Development :: Internationalization
Classifier: Topic :: Software Development :: Libraries :: Python Modules
Classifier: Topic :: Software Development :: Localization
Classifier: Topic :: Text Processing :: Linguistic
